cnnecharts/__init__.py
cnnecharts/chartOptions.py
cnnecharts/charts.py
cnnecharts/components.py
cnnecharts/mapping.py
cnnecharts/optionCaller.py
cnnecharts/props.py
cnnecharts/seriesProps.py
cnnecharts/spec.py
cnnecharts/templates/fileRender.html
cnnecharts/templates/themes/macarons.json
cnnecharts/utils/__init__.py
cnnecharts/utils/baseInfos.py
cnnecharts/utils/data_gen.py
cnnecharts/utils/renders.py
cnnecharts-0.1.11.data/data/templates/fileRender.html
cnnecharts-0.1.11.data/data/templates/macarons.json
cnnecharts-0.1.11.dist-info/LICENSE
cnnecharts-0.1.11.dist-info/METADATA
cnnecharts-0.1.11.dist-info/WHEEL
cnnecharts-0.1.11.dist-info/top_level.txt
cnnecharts-0.1.11.dist-info/RECORD
